restartable_lambda/__init__.py
restartable_lambda/restartable_lambda_module.py
restartable_lambda-0.0.13.dist-info/METADATA
restartable_lambda-0.0.13.dist-info/WHEEL
restartable_lambda-0.0.13.dist-info/top_level.txt
restartable_lambda-0.0.13.dist-info/RECORD
