Metadata-Version: 2.1
Name: restartable-lambda
Version: 0.0.13
Summary: Allow to create restartable lambda
Author: Samuel Courthial
Author-email: samuel.courthial.18@gmail.com
Keywords: python,aws,lambda,restartable,restart,boto3
Classifier: Programming Language :: Python :: 2
Classifier: Programming Language :: Python :: 3
Requires-Dist: boto3 ==1.23.10
Requires-Dist: retrying ==1.3.3
